{
  "committee_roles": [
    {
      "permissionLevel": "Full Access",
      "name": "Chairperson",
      "id": "r-chair",
      "description": "Ruhusa kamili ya uendeshaji, kuongeza wanakamati, na uandikishaji wa malipo."
    },
    {
      "name": "Treasurer",
      "id": "r-treasurer",
      "description": "Uandikishaji na usimamizi wa malipo pekee, hawezi kufuta muamala au kubadili wajumbe.",
      "permissionLevel": "Treasurer Access"
    },
    {
      "name": "Secretary",
      "description": "Kusoma wageni pekee na kutoa taarifa na ripoti tofauti za kamati kusaidia mwenyekiti.",
      "id": "r-secretary",
      "permissionLevel": "Viewer Access"
    },
    {
      "name": "Committee Member",
      "id": "r-member",
      "description": "Kutazama michango kwa ujumla na chati, taarifa za siri za kila mchangiaji zinalindwa.",
      "permissionLevel": "Summary Access"
    }
  ],
  "committee_members": [
    {
      "permissionLevel": "Full Access",
      "phone": "0711223344",
      "email": "james@gmail.com",
      "name": "James Lema",
      "token": "m-james",
      "position": "Chairperson",
      "id": "c-1"
    },
    {
      "position": "Treasurer",
      "id": "c-2",
      "token": "m-salma",
      "name": "Salma Khamis",
      "email": "salma@treasury.co.tz",
      "phone": "0755998877",
      "permissionLevel": "Treasurer Access"
    },
    {
      "permissionLevel": "Viewer Access",
      "phone": "0766332211",
      "email": "shija@sec.org",
      "name": "Emmanuel Shija",
      "position": "Secretary",
      "token": "m-emmanu",
      "id": "c-3"
    },
    {
      "phone": "0688445566",
      "permissionLevel": "Summary Access",
      "id": "c-4",
      "position": "Committee Member",
      "token": "m-aisha",
      "name": "Aisha Ramadhani",
      "email": "aisha@kamati.co.tz"
    }
  ],
  "eventDetails": {},
  "smsGatewaySettings": {
    "provider": "meseji",
    "url": "https://meseji.co.tz/api/v1/sms/send",
    "apiKey": "zs_0e48ae894d0a6a379717f7f68095928c2c84243cc181b9fe",
    "apiSecret": "",
    "senderId": "EVENT CARD",
    "senderIdStatus": "approved",
    "whatsappUrl": "",
    "customHeaders": "{}",
    "customBody": "{\n  \"to\": \"{to}\",\n  \"message\": \"{message}\"\n}"
  },
  "deletedGuestIds": [
    "G-852725",
    "G-760552",
    "G-299241",
    "G-299246",
    "G-299251",
    "G-299255",
    "G-299260",
    "G-299264",
    "G-299274",
    "G-299279",
    "G-299283",
    "G-299288",
    "G-299293",
    "G-299298",
    "G-299307",
    "G-299313",
    "G-299317",
    "G-299322",
    "G-299326",
    "G-299331",
    "G-299336",
    "G-299340",
    "G-299345",
    "G-299349",
    "G-299354",
    "G-299358",
    "G-299363",
    "G-299367",
    "G-299375",
    "G-299379",
    "G-299383",
    "G-299387",
    "G-299392",
    "G-299398",
    "G-299402",
    "G-299406",
    "G-299410",
    "G-299415",
    "G-299421",
    "G-299425",
    "G-299429",
    "G-299434",
    "G-299439",
    "G-299445",
    "G-299450",
    "G-299454",
    "G-299465",
    "G-299472"
  ],
  "guests": [],
  "eventsList": [],
  "saveTheDates": [],
  "saveTheDateRecipients": [],
  "templateSettings": {}
}